<?xml version="1.0" encoding="utf-8"?>
<Gesture>
  <Sample Samples="32" />
  <Size Size="3.627748" />
  <Templates>
    <Point x="0.768950939" y="1.92868364" />
    <Point x="0.3610638" y="2.22878647" />
    <Point x="-0.0996788442" y="2.428609" />
    <Point x="-0.5958345" y="2.49416018" />
    <Point x="-1.07150459" y="2.34408331" />
    <Point x="-1.47001922" y="2.02065754" />
    <Point x="-1.81722093" y="1.63518417" />
    <Point x="-2.159211" y="1.24506176" />
    <Point x="-2.39891529" y="0.7792877" />
    <Point x="-2.51366282" y="0.259602427" />
    <Point x="-2.41286659" y="-0.262594342" />
    <Point x="-2.21386123" y="-0.7519234" />
    <Point x="-1.99035192" y="-1.23056591" />
    <Point x="-1.73544967" y="-1.69071543" />
    <Point x="-1.39788735" y="-2.08312917" />
    <Point x="-0.95800674" y="-2.33143663" />
    <Point x="-0.470582277" y="-2.44840813" />
    <Point x="0.0265573263" y="-2.50583982" />
    <Point x="0.5256808" y="-2.478813" />
    <Point x="1.01677454" y="-2.384204" />
    <Point x="1.46047211" y="-2.13633966" />
    <Point x="1.81608" y="-1.76480389" />
    <Point x="2.06569624" y="-1.30096436" />
    <Point x="2.33679748" y="-0.8512802" />
    <Point x="2.48633718" y="-0.3432563" />
    <Point x="2.47526717" y="0.18650353" />
    <Point x="2.28802347" y="0.6814064" />
    <Point x="1.98695791" y="1.10481727" />
    <Point x="1.68277276" y="1.52294409" />
    <Point x="1.24341738" y="1.77932918" />
    <Point x="0.764202833" y="1.92515719" />
  </Templates>
  <Start_End>
    <Start StartPos_x="0.768950939" StartPos_y="1.92868364" />
    <End EndPos_x="0.764202833" EndPos_y="1.92515719" />
  </Start_End>
</Gesture>